Metadata-Version: 2.4
Name: django-heralder
Version: 0.4.2
Summary: Django library for separating the message content from transmission method.
Project-URL: Homepage, https://github.com/peterfarrell/django-heralder
Project-URL: Repository, https://github.com/peterfarrell/django-heralder.git
Project-URL: Issues, https://github.com/peterfarrell/django-heralder/issues
Project-URL: Changelog, https://github.com/peterfarrell/django-heralder/blob/main/CHANGELOG.md
Author-email: PJ Farrell <pj@mariska.dev>
License-Expression: MIT
License-File: LICENSE
Keywords: django,messaging,notifications
Classifier: Development Status :: 5 - Production/Stable
Classifier: Framework :: Django
Classifier: Framework :: Django :: 3.2
Classifier: Framework :: Django :: 4.2
Classifier: Framework :: Django :: 5.2
Classifier: Intended Audience :: Developers
Classifier: License :: OSI Approved :: MIT License
Classifier: Programming Language :: Python
Classifier: Programming Language :: Python :: 3
Classifier: Programming Language :: Python :: 3 :: Only
Classifier: Programming Language :: Python :: 3.10
Classifier: Programming Language :: Python :: 3.11
Classifier: Programming Language :: Python :: 3.12
Classifier: Programming Language :: Python :: 3.13
Requires-Python: <3.14,>=3.10
Requires-Dist: django<=5.2,>=3.2
Requires-Dist: jsonpickle>=4.1.1
Provides-Extra: html2text
Requires-Dist: html2text>=2025.2.26; extra == 'html2text'
Provides-Extra: twilio
Requires-Dist: twilio>=8.11.1; extra == 'twilio'
